fa.v
// Full Adder Module

module fa( input a, b, cin, output s, cout );
    assign s = a ^ b ^ cin;         // XOR for difference
    assign cout = a & b | (a ^ b) & cin;      // AND with negated minuend for borrow
endmodule

fa_tb.v
/* Test_bench for FA 
saved in file fa_tb.v*/

`include "fa.v" // The include directive is used to include the contents of one file into another during preprocessing.

module fa_tb;
    reg a, b, cin;
    wire s, cout;

    fa fa1(a,b,cin,s,cout);

    initial begin  //'begin & 'end' are not required for 1 line code
        $dumpfile("fa.vcd"); // vcd - value change dump
        $dumpvars(0,fa_tb);


        a = 0; b = 0; cin = 0; #1
        a = 0; b = 0; cin = 1; #1
        a = 0; b = 1; cin = 0; #1
        a = 0; b = 1; cin = 1; #1
        a = 1; b = 0; cin = 0; #1
        a = 1; b = 0; cin = 1; #1
        a = 1; b = 1; cin = 0; #1
        a = 1; b = 1; cin = 1; #1

        $finish; // End of simulation
        end
endmodule

fa.vcd
$date
	Fri Jan 03 15:28:40 2025
$end
$version
	Icarus Verilog
$end
$timescale
	1s
$end
$scope module fa_tb $end
$var wire 1 ! s $end
$var wire 1 " cout $end
$var reg 1 # a $end
$var reg 1 $ b $end
$var reg 1 % cin $end
$scope module fa1 $end
$var wire 1 # a $end
$var wire 1 $ b $end
$var wire 1 % cin $end
$var wire 1 " cout $end
$var wire 1 ! s $end
$upscope $end
$upscope $end
$enddefinitions $end
$comment Show the parameter values. $end
$dumpall
$end
#0
$dumpvars
0%
0$
0#
0"
0!
$end
#1
1!
1%
#2
0%
1$
#3
1"
0!
1%
#4
0"
1!
0%
0$
1#
#5
1"
0!
1%
#6
0%
1$
#7
1!
1%
